README.md
setup.cfg
setup.py
duffel/__init__.py
duffel/base_utils.py
duffel/col.py
duffel/df.py
duffel/index.py
duffel/loc.py
duffel/na.py
duffel/row.py
duffel/utils.py
duffel.egg-info/PKG-INFO
duffel.egg-info/SOURCES.txt
duffel.egg-info/dependency_links.txt
duffel.egg-info/not-zip-safe
duffel.egg-info/top_level.txt
duffel/fake_data/__init__.py